odoo10_addon_sale_commission_geo_assign-10.0.1.0.0.99.dev4-py3.8-nspkg.pth
odoo/addons/sale_commission_geo_assign/README.rst
odoo/addons/sale_commission_geo_assign/__init__.py
odoo/addons/sale_commission_geo_assign/__manifest__.py
odoo/addons/sale_commission_geo_assign/i18n/sale_commission_geo_assign.pot
odoo/addons/sale_commission_geo_assign/models/__init__.py
odoo/addons/sale_commission_geo_assign/models/res_partner.py
odoo/addons/sale_commission_geo_assign/readme/CONFIGURE.rst
odoo/addons/sale_commission_geo_assign/readme/DESCRIPTION.rst
odoo/addons/sale_commission_geo_assign/readme/USAGE.rst
odoo/addons/sale_commission_geo_assign/static/description/icon.png
odoo/addons/sale_commission_geo_assign/static/description/index.html
odoo/addons/sale_commission_geo_assign/tests/__init__.py
odoo/addons/sale_commission_geo_assign/tests/test_sale_commission_geo_assign.py
odoo/addons/sale_commission_geo_assign/views/res_partner_view.xml
odoo/addons/sale_commission_geo_assign/wizard/__init__.py
odoo/addons/sale_commission_geo_assign/wizard/wizard_geo_assign_partner.py
odoo/addons/sale_commission_geo_assign/wizard/wizard_geo_assign_partner_view.xml
odoo10_addon_sale_commission_geo_assign-10.0.1.0.0.99.dev4.dist-info/METADATA
odoo10_addon_sale_commission_geo_assign-10.0.1.0.0.99.dev4.dist-info/WHEEL
odoo10_addon_sale_commission_geo_assign-10.0.1.0.0.99.dev4.dist-info/namespace_packages.txt
odoo10_addon_sale_commission_geo_assign-10.0.1.0.0.99.dev4.dist-info/top_level.txt
odoo10_addon_sale_commission_geo_assign-10.0.1.0.0.99.dev4.dist-info/RECORD
