Metadata-Version: 2.1
Name: odoo10-addon-sale-commission-geo-assign
Version: 10.0.1.0.0.99.dev4
Summary: Assign agents to partners according to their location
Home-page: https://github.com/OCA/commission
Author: Agile Business Group, Odoo Community Association (OCA)
Author-email: support@odoo-community.org
License: LGPL-3
Platform: UNKNOWN
Classifier: Programming Language :: Python
Classifier: Framework :: Odoo
Classifier: Framework :: Odoo :: 10.0
Classifier: License :: OSI Approved :: GNU Lesser General Public License v3 (LGPLv3)
Classifier: Development Status :: 5 - Production/Stable
Requires-Python: ~=2.7
Requires-Dist: odoo10-addon-sale-commission
Requires-Dist: odoo <10.1dev,>=10.0
